Metadata-Version: 1.1
Name: loremipsum
Version: 1.0.4
Summary: UNKNOWN
Home-page: http://projects.monkeython.com/loremipsum
Author: Luca De Vitis
Author-email: luca@monkeython.com
License: UNKNOWN
Keywords: lorem,ipsum,text,generator
Platform: UNKNOWN
Classifier: Development Status :: 5 - Production/Stable
Classifier: Intended Audience :: Developers
Classifier: License :: OSI Approved :: GNU General Public License (GPL)
Classifier: Operating System :: OS Independent
Classifier: Programming Language :: Python :: 2.5
Classifier: Programming Language :: Python :: 2.6
Classifier: Programming Language :: Python :: 2.7
Classifier: Topic :: Software Development :: Libraries :: Python Modules
